patch_float.py
patch_json_float-0.3.dist-info/METADATA
patch_json_float-0.3.dist-info/WHEEL
patch_json_float-0.3.dist-info/top_level.txt
patch_json_float-0.3.dist-info/RECORD
