Metadata-Version: 2.1
Name: patch-json-float
Version: 0.3
Summary: patch builtins float class
Home-page: https://github.com/weaming/patch-json-float
Author: weaming
Author-email: garden.yuen@gmail.com
License: UNKNOWN
Project-URL: Source, https://github.com/weaming/patch-json-float
Project-URL: Bug Reports, https://github.com/weaming/patch-json-float
Keywords: monkey-patch,patch,developer
Platform: UNKNOWN
